farmhash.cp310-win_amd64.pyd
pyfarmhash-0.4.0.dist-info/LICENSE
pyfarmhash-0.4.0.dist-info/METADATA
pyfarmhash-0.4.0.dist-info/WHEEL
pyfarmhash-0.4.0.dist-info/top_level.txt
pyfarmhash-0.4.0.dist-info/RECORD
