Metadata-Version: 2.1
Name: pyfarmhash
Version: 0.4.0
Summary: Google FarmHash Bindings for Python
Home-page: https://github.com/veelion/python-farmhash
Author: Veelion Chong
Author-email: veelion@gmail.com
Keywords: farmhash,google
Classifier: Development Status :: 5 - Production/Stable
Classifier: License :: OSI Approved :: MIT License
Classifier: Intended Audience :: Developers
Classifier: Programming Language :: C
Classifier: Programming Language :: Python
Classifier: Programming Language :: Python :: 2.6
Classifier: Programming Language :: Python :: 2.7
Classifier: Programming Language :: Python :: 3.7
Classifier: Programming Language :: Python :: 3.8
Classifier: Programming Language :: Python :: 3.9
Classifier: Programming Language :: Python :: 3.10
Classifier: Programming Language :: Python :: 3.11
License-File: LICENSE
